simplegeomap/GSHHS_l_L2.dbf
simplegeomap/GSHHS_l_L2.prj
simplegeomap/GSHHS_l_L2.shp
simplegeomap/GSHHS_l_L2.shx
simplegeomap/TM_WORLD_BORDERS-0.3.dbf
simplegeomap/TM_WORLD_BORDERS-0.3.shp
simplegeomap/WDBII_river_c_L02.dbf
simplegeomap/WDBII_river_c_L02.prj
simplegeomap/WDBII_river_c_L02.shp
simplegeomap/WDBII_river_c_L02.shx
simplegeomap/__init__.py
simplegeomap/all_countries.csv
simplegeomap/cities.zip
simplegeomap/continents.zip
simplegeomap/g10g.npz
simplegeomap/simplegeomap.py
simplegeomap/util.py
simplegeomap-0.0.37.dist-info/METADATA
simplegeomap-0.0.37.dist-info/WHEEL
simplegeomap-0.0.37.dist-info/top_level.txt
simplegeomap-0.0.37.dist-info/RECORD
