Metadata-Version: 2.1
Name: simplegeomap
Version: 0.0.37
Summary: Simple offline map plot utility, for country borders, elevation, water
Home-page: https://github.com/burakbayramli/simplegeomap
Author: Burak Bayramli
License: UNKNOWN
Platform: UNKNOWN
Requires-Dist: pandas
Requires-Dist: pygeodesy
Requires-Dist: matplotlib
Requires-Dist: numpy
Requires-Dist: pyshp
Requires-Dist: zarr
Requires-Dist: Pillow
